[
  {
    "url": "http://www.mckusick.com/"
  },
  {
    "url": "http://atrey.karlin.mff.cuni.cz/"
  },
  {
    "url": "https://www.templetons.com/brad"
  },
  {
    "url": "http://webarchive.me/geocities/Tokyo/Harbor/2814/main.html"
  },
  {
    "url": "https://www.w3.org/People/Bos"
  },
  {
    "url": "https://ee.stanford.edu/~hellman"
  },
  {
    "url": "http://webdocs.cs.ualberta.ca/~games"
  },
  {
    "url": "https://www.qupola.com/"
  },
  {
    "url": "https://www.gamers.org/dEngine"
  },
  {
    "url": "https://www.philohome.com/"
  },
  {
    "url": "http://walterbright.com/"
  },
  {
    "url": "http://olivercowdery.com/smithhome/smithdig.htm"
  },
  {
    "url": "http://number-none.com/blow"
  },
  {
    "url": "http://www.trailquest.net/"
  },
  {
    "url": "https://www.legends-station.com/"
  },
  {
    "url": "http://patrickaalto.com/PAmain.html"
  },
  {
    "url": "https://the-em-dash.com/"
  },
  {
    "url": "https://www.jayfisher.com/"
  },
  {
    "url": "http://www.goliathindustries.com/vb"
  },
  {
    "url": "http://graham.freeservers.com/"
  },
  {
    "url": "http://jgeoff.com/homepage"
  },
  {
    "url": "http://www.mia.org.il/"
  },
  {
    "url": "https://flownet.com/ron"
  },
  {
    "url": "http://www.hawaii.edu/powerkills"
  },
  {
    "url": "http://cm.bell-labs.co/who/dmr"
  },
  {
    "url": "http://kelesis.free.fr/hp/compile/index_eng.htm"
  },
  {
    "url": "https://www.pas.rochester.edu/~dmw"
  },
  {
    "url": "http://www.deater.net/weave"
  },
  {
    "url": "http://eagb.net/advance"
  },
  {
    "url": "http://members.madasafish.com/~cj_whitehound"
  },
  {
    "url": "http://users.csc.calpoly.edu/~zwood"
  },
  {
    "url": "https://sites.pitt.edu/~dash/ashliman.html"
  },
  {
    "url": "https://www.linfo.org/"
  },
  {
    "url": "http://worth.bol.ucla.edu/"
  },
  {
    "url": "https://abaduaber.com/"
  },
  {
    "url": "http://www.tifaq.org/"
  },
  {
    "url": "https://wuzzy.codeberg.page/"
  },
  {
    "url": "http://www.gregdonner.org/"
  },
  {
    "url": "https://nohup.io/"
  },
  {
    "url": "https://www.protopopov.lv/en"
  },
  {
    "url": "https://mammana.org/"
  },
  {
    "url": "https://giankarl941.github.io/giankarl"
  },
  {
    "url": "https://worldofmatthew.com/computing/decline"
  },
  {
    "url": "http://www.sysctl.org/"
  },
  {
    "url": "http://mattisbeck.com/"
  },
  {
    "url": "https://oskog97.com/"
  },
  {
    "url": "http://doslovaja.cz/"
  },
  {
    "url": "https://supercoolnet.neocities.org/"
  },
  {
    "url": "https://in-th3-l00p.github.io/web"
  },
  {
    "url": "https://eintr.net/"
  },
  {
    "url": "https://aj.bozdar.im/"
  },
  {
    "url": "https://joshuagarner.xyz/"
  },
  {
    "url": "https://supercoolnet.neocities.org/opinions"
  },
  {
    "url": "https://aadithyancodes.vercel.app/"
  },
  {
    "url": "https://mammana.org/hello"
  },
  {
    "url": "http://www.edutech.org.tw/"
  },
  {
    "url": "https://dataswamp.org/~lich"
  },
  {
    "url": "http://home.macintosh.garden/~s0s"
  },
  {
    "url": "https://website-example.codeberg.page/"
  },
  {
    "url": "https://chrisruppel.com/blog/receiving-webmentions"
  },
  {
    "url": "http://www.gregdonner.org/thoughts/kurt_cobain_explanation.html"
  },
  {
    "url": "https://nuwen.net/download.html"
  },
  {
    "url": "http://compucolor.org/links.html"
  },
  {
    "url": "https://secretonions.neocities.org/"
  },
  {
    "url": "https://flamedfury.com/links"
  },
  {
    "url": "https://neustadt.fr/essays/the-small-web"
  },
  {
    "url": "https://bebyx.co.ua/en"
  },
  {
    "url": "https://dpolakovic.space/"
  },
  {
    "url": "http://sdf.org/~pkal"
  },
  {
    "url": "https://www.davidschlachter.com/"
  },
  {
    "url": "https://www.alexandertalk.com/robert.html"
  },
  {
    "url": "https://barryfrost.com/"
  },
  {
    "url": "https://zbox.neocities.org/"
  },
  {
    "url": "http://www.willegal.net/"
  },
  {
    "url": "https://www.simoneklemm.de/menue.htm"
  },
  {
    "url": "http://skywoof.com/aru/ele1p.htm"
  },
  {
    "url": "https://www.simoneklemm.de/"
  },
  {
    "url": "https://lcamtuf.coredump.cx/gcnc"
  },
  {
    "url": "http://www.willegal.net/index.htm"
  },
  {
    "url": "https://hodgy.net/"
  },
  {
    "url": "https://www.ffs.net/gdhm"
  },
  {
    "url": "http://harmonyzone.org/RMDictionary/RMDictionary.html"
  },
  {
    "url": "http://www.sidneyrigdon.com/dbroadhu/UT/tribune2.htm"
  },
  {
    "url": "http://soft14.com/"
  },
  {
    "url": "https://www.scandig.info/Literatur.html"
  },
  {
    "url": "http://ninfinger.org/rockets/rmrfaq.11.html"
  },
  {
    "url": "https://zerocontradictions.net/misc/contact"
  },
  {
    "url": "https://ctrl-c.club/~singletona082"
  },
  {
    "url": "http://a2retrosystems.com/support.htm"
  },
  {
    "url": "https://stason.org/TULARC/radio/shortwave"
  },
  {
    "url": "http://www.6502.org/tools/asm"
  },
  {
    "url": "https://www.bttr-software.de/freesoft/dbase.htm"
  },
  {
    "url": "http://www.solomonspalding.com/docs/braden/1884BnKf.htm"
  },
  {
    "url": "http://www.linuxfocus.org/"
  },
  {
    "url": "http://kitbash.net/"
  },
  {
    "url": "http://why2k.de/"
  },
  {
    "url": "http://www.sidneyrigdon.com/dbroadhu/CA/natruths.htm"
  },
  {
    "url": "https://susansenator.com/"
  },
  {
    "url": "https://www.fiwix.org/"
  },
  {
    "url": "http://earmark.net/gesr/Current_Radio_Design.htm"
  },
  {
    "url": "http://www.minsocam.org/MSA/collectors_corner"
  },
  {
    "url": "http://mtthw.net/travel/riga2023.html"
  },
  {
    "url": "https://10kb.neocities.org/gallery/0033"
  },
  {
    "url": "https://www.schmuck-boerse.com/index-edelstein-diamant.htm"
  },
  {
    "url": "https://retronode.org/"
  },
  {
    "url": "https://trashchan.xyz/retro/index.html"
  },
  {
    "url": "http://86box.net/"
  },
  {
    "url": "http://m.retronetwork.net/"
  },
  {
    "url": "https://www.retro-exo.com/"
  },
  {
    "url": "http://elektromechanischmuseum.nl/retro"
  },
  {
    "url": "https://baloo.neocities.org/TheGuide/TheGuide-Part6"
  },
  {
    "url": "http://3rz.de/"
  },
  {
    "url": "https://iroiro.neocities.org/"
  },
  {
    "url": "http://www.creopard.de/"
  },
  {
    "url": "http://www.retroisle.com/"
  },
  {
    "url": "http://felix.plesoianu.ro/web/stark-retro.html"
  },
  {
    "url": "http://www.digitpress.com/"
  },
  {
    "url": "http://jbr.me.uk/retro"
  },
  {
    "url": "https://cobradile.neocities.org/"
  },
  {
    "url": "https://jonathan-allright.neocities.org/"
  },
  {
    "url": "http://www.retronetwork.net/html4"
  },
  {
    "url": "https://www.neo-geo.com/"
  },
  {
    "url": "https://eligood.neocities.org/"
  },
  {
    "url": "http://lucifer.n8fq.org/"
  },
  {
    "url": "https://www.fatefullore.com/"
  },
  {
    "url": "https://retroandreformed.neocities.org/"
  },
  {
    "url": "https://baloo.neocities.org/TheGuide/TheGuide-Part2"
  },
  {
    "url": "https://baloo.neocities.org/TheGuide/TheGuide-Part1"
  },
  {
    "url": "https://www.retro-sanctuary.com/"
  },
  {
    "url": "https://kdelaney.neocities.org/"
  },
  {
    "url": "http://retro.maniek86.xyz/"
  },
  {
    "url": "http://geryon.n8fq.org/"
  },
  {
    "url": "https://iroiro.neocities.org/links"
  },
  {
    "url": "https://bignerdsam.neocities.org/"
  },
  {
    "url": "https://rcsri.org/rcs-info.shtml"
  },
  {
    "url": "http://inverary.net/Home/inverary.php"
  },
  {
    "url": "http://manfred.ueuo.com/"
  },
  {
    "url": "http://www.imarshall.karoo.net/"
  },
  {
    "url": "http://margiolis.net/w/oldweb"
  },
  {
    "url": "https://oldwebimages.online/archive.html"
  },
  {
    "url": "https://devon.lol/blog/the-old-web"
  },
  {
    "url": "http://petermolnar.net/article/old-web-new-web-indie-web"
  },
  {
    "url": "http://koshka.love/babel/divergent-thinking.html"
  },
  {
    "url": "http://www.furmannet.net/aboutme.htm"
  },
  {
    "url": "https://sivasubramanian.me/"
  },
  {
    "url": "https://ari-blenkhorn.github.io/old_cmu_site"
  },
  {
    "url": "https://kithala.neocities.org/"
  },
  {
    "url": "https://bytemoth.neocities.org/webrings"
  },
  {
    "url": "https://www.donwiss.com/pictures/BrooklynStores"
  },
  {
    "url": "https://blissnet.neocities.org/"
  },
  {
    "url": "https://tapeykatt.neocities.org/home"
  },
  {
    "url": "https://frutigeraeroarchive.org/resources"
  },
  {
    "url": "http://koshka.love/"
  },
  {
    "url": "https://www.biopsychiatry.com/antidepressants"
  },
  {
    "url": "http://infolab.stanford.edu/~backrub/google.html"
  },
  {
    "url": "https://3dkingdoms.com/checkers.htm"
  },
  {
    "url": "https://projects.kwon.nyc/internet-is-fun"
  },
  {
    "url": "https://www.musicpd.org/clients"
  },
  {
    "url": "https://lukesmith.neocities.org/vids/dead_net"
  },
  {
    "url": "https://noxz.tech/"
  },
  {
    "url": "https://crft.sh/"
  },
  {
    "url": "https://n0thanky0u.neocities.org/theoldweb"
  },
  {
    "url": "http://www.k58.uk/pages/stuff/old-computer-challenge-v3.html"
  },
  {
    "url": "https://www.charitybailey.org/"
  },
  {
    "url": "https://linkyblog.neocities.org/9-5-2021post"
  },
  {
    "url": "http://bostjan-grandovec.si/Content/News.htm"
  },
  {
    "url": "https://autumnsgrace.neocities.org/"
  },
  {
    "url": "http://www.therockshows.com/"
  },
  {
    "url": "https://fromthesuperhighway.com/"
  },
  {
    "url": "https://frutigeraeroarchive.org/aero_webring"
  },
  {
    "url": "http://colincogle.name/blog/the-small-web"
  },
  {
    "url": "https://brisray.com/web/webring-list.htm"
  },
  {
    "url": "https://www.scriptarchive.com/guestbook.html"
  },
  {
    "url": "https://buruma.net/guestbook/gbook.php"
  },
  {
    "url": "http://kalechips.net/contact"
  },
  {
    "url": "http://kolesnikov.se/guestbook.html"
  },
  {
    "url": "http://www.kerchner.com/add.htm"
  },
  {
    "url": "http://www.espace.org/guest/larchive/larchive.html"
  },
  {
    "url": "http://www.final-fantasy.it/geobook.html"
  },
  {
    "url": "http://www.leospage.de/animemanga/gbook_old.htm"
  },
  {
    "url": "http://www.abhota.info/guestbk.htm"
  },
  {
    "url": "http://www.furmannet.net/sites/guestbook"
  },
  {
    "url": "http://www.maplecity.com/homepage/guest.html"
  },
  {
    "url": "http://timrusstribute.com/Guestbook.htm"
  },
  {
    "url": "https://atabook.org/"
  },
  {
    "url": "http://www.voy.com/755"
  },
  {
    "url": "https://koi.rip/guestbook"
  },
  {
    "url": "https://greg-kennedy.com/history/na/fsguestbook.html"
  },
  {
    "url": "http://www.nick99nack.com/guestbook/view_guestbook.asp"
  },
  {
    "url": "https://www.cayzle.com/screeds/guestbook.html"
  },
  {
    "url": "http://www.remembertheafl.com/AFLGuestBook.htm"
  },
  {
    "url": "http://lightning.nu/book"
  },
  {
    "url": "http://www.chachich.com/mdchachi/gbadd09.html"
  },
  {
    "url": "https://www.packrat-pro.com/guestbook/PRguest.htm"
  },
  {
    "url": "https://zimage.com/~ant/antfarm/oldgb.html"
  },
  {
    "url": "http://www.preachtheoldpaths.com/guestbook-/guestbook-.html"
  },
  {
    "url": "http://ecctechservice.com/Byrds/guestboo.htm"
  },
  {
    "url": "https://www.smartgb.com/"
  },
  {
    "url": "https://zimage.com/~ant/antfarm/oldgb2.html"
  },
  {
    "url": "https://www.smartgb.com/?p=newtoplink2"
  },
  {
    "url": "http://kalechips.net/"
  },
  {
    "url": "http://www.geocities.ws/jwyg/index-2.html"
  },
  {
    "url": "https://freemasonrywatch.org/"
  },
  {
    "url": "https://nerdymom.neocities.org/"
  },
  {
    "url": "http://lolwut.info/comp/youtube/ytp.html"
  },
  {
    "url": "https://www2.b3ta.com/realistic-internet-simulator"
  },
  {
    "url": "https://www.mirc.co.uk/"
  },
  {
    "url": "http://www.hoppe.biz/en"
  },
  {
    "url": "https://www.highcriteria.com/"
  },
  {
    "url": "http://global.sharp/inet-viewcam/text/sample.html"
  },
  {
    "url": "https://sandwich.net/"
  },
  {
    "url": "http://pixeljoint.com/"
  },
  {
    "url": "https://aeb.win.tue.nl/linux/kbd/scancodes-6.html"
  },
  {
    "url": "http://www.nic.funet.fi/index/FUNET/history/internet/en"
  },
  {
    "url": "https://ledudu.com/casiopb700/casiopb700.htm"
  },
  {
    "url": "https://jl.ly/"
  },
  {
    "url": "http://www.lolwut.info/comp/newgrounds/pimp.html"
  },
  {
    "url": "http://streetpavement.com/"
  },
  {
    "url": "https://www.plig.net/"
  },
  {
    "url": "https://mohit.uk/work/written-files/freedomspeech2021.html"
  },
  {
    "url": "https://www.dreael.ch/Deutsch/Wegweiser"
  },
  {
    "url": "http://dir.pepesearch.com/"
  },
  {
    "url": "http://www.icab.de/"
  },
  {
    "url": "http://idownload.ws/"
  },
  {
    "url": "http://yusearch.com/"
  },
  {
    "url": "https://www.orpheusinternet.co.uk/voip/index.html"
  },
  {
    "url": "https://arachnoid.com/freezone"
  },
  {
    "url": "https://www.ch.ic.ac.uk/rzepa/ecsoc/30300094.htm"
  },
  {
    "url": "http://www.macorchard.com/"
  },
  {
    "url": "https://www.rfc-editor.org/rfc/rfc6724"
  },
  {
    "url": "http://www.lolwut.info/comp/newgrounds/sunshine-crew.html"
  },
  {
    "url": "https://homepages.cwi.nl/~steven/amsterdam.html"
  },
  {
    "url": "http://www.oldskool.org/guides/tvdog/internet.html"
  },
  {
    "url": "https://fast.com/"
  },
  {
    "url": "http://www.ways-of-christ.net/search.htm"
  },
  {
    "url": "https://www.piseries.com/"
  },
  {
    "url": "http://www.turnofftheinternet.com/"
  },
  {
    "url": "https://www.mrspeaker.net/"
  },
  {
    "url": "http://toastytech.com/evil/ieerrors.html"
  },
  {
    "url": "http://www.scubamom.com/midis/caribbean"
  },
  {
    "url": "https://jacobsm.com/"
  },
  {
    "url": "http://www.groovynet.com/"
  },
  {
    "url": "http://www.silverhillala.com/judith/midis.html"
  },
  {
    "url": "https://soulmaze.neocities.org/about"
  },
  {
    "url": "https://linuxfr.org/journaux"
  },
  {
    "url": "http://www.geocities.ws/pikachuscript"
  },
  {
    "url": "http://ultimatemm3.mchenrygames.com/"
  },
  {
    "url": "https://cammy.somnolescent.net/underground"
  },
  {
    "url": "https://www.jesus-is-savior.com/Miscellaneous/create_your_own_website.htm"
  },
  {
    "url": "http://www.old-hippie.com/sound_files/pg/pgm/gen.html"
  },
  {
    "url": "http://webarchive.me/geocities/Area51/Dunes/1021"
  },
  {
    "url": "http://classicyes.net/others.html"
  },
  {
    "url": "http://www.geocities.ws/CollegePark/1588/ranma.html"
  },
  {
    "url": "http://asteride.xyz/articles/depre_temps_hexadecimal.html"
  },
  {
    "url": "https://charbomber.neocities.org/"
  },
  {
    "url": "http://webarchive.me/geocities/Tokyo/Lights/8912"
  },
  {
    "url": "https://obspogon.neocities.org/megacol"
  },
  {
    "url": "http://www.mario-mania.50megs.com/"
  },
  {
    "url": "http://koshka.love/babel/creating-a-website.html"
  },
  {
    "url": "http://webarchive.me/geocities/Tokyo/Pagoda/6617"
  },
  {
    "url": "https://www.captainpackrat.com/furry"
  },
  {
    "url": "http://melaman2.com/oldiesmusic/sixties.html"
  },
  {
    "url": "http://knuckleschaotix.net/music.htm"
  },
  {
    "url": "http://koshka.love/babel/web-design-principles.html"
  },
  {
    "url": "http://www.users.globalnet.co.uk/~brlowe"
  },
  {
    "url": "https://popuw.com/news.html"
  },
  {
    "url": "http://koshka.love/links.html"
  },
  {
    "url": "https://midimusic.github.io/wurlitzer/miditzer-archive"
  },
  {
    "url": "http://www.psilocybindreams.com/pc/midi"
  },
  {
    "url": "https://mudcat.org/"
  },
  {
    "url": "https://wings.nu/nostalgia/readable.php"
  },
  {
    "url": "http://www.kashue.com/"
  },
  {
    "url": "http://tilde.town/~netscape_navigator"
  },
  {
    "url": "http://www.andrewturnbull.net/mozilla/history.html"
  },
  {
    "url": "http://scripting.com/davenet/1999/06/16/aFaceOffWithNetscape.html"
  },
  {
    "url": "http://www.blooberry.com/indexdot/history/netscape.htm"
  },
  {
    "url": "https://litux.nl/mirror/csscookbook/0596005768/cssckbk-CHP-9-SECT-1.html"
  },
  {
    "url": "http://home.mcom.com/home/welcome.html"
  },
  {
    "url": "https://useragentstring.com/"
  },
  {
    "url": "http://sites.utoronto.ca/webdocs/HTMLdocs/Book/Book-3ed/appf/color2.html"
  },
  {
    "url": "http://biomodel.uah.es/comun/compatib/netscape.htm"
  },
  {
    "url": "http://www.free.net/Docs/cyrillic/notes.en.html"
  },
  {
    "url": "http://www.floodgap.com/retrotech/machten/mosaic"
  },
  {
    "url": "https://seirdy.one/meta/site-design"
  },
  {
    "url": "http://the-light.com/colclick.html"
  },
  {
    "url": "http://www.jurema-sampaio.pro.br/aulas/Arquitec/Aula02/tutorial-composer.html"
  },
  {
    "url": "http://home.mcom.com/home/manual_docs/legal.html"
  },
  {
    "url": "http://home.olemiss.edu/~mudws/font.html"
  },
  {
    "url": "http://www.geocities.ws/MotorCity/Track/4148"
  },
  {
    "url": "http://www.catb.org/~esr/open-source.html"
  },
  {
    "url": "http://lightner.net/manxclub"
  },
  {
    "url": "http://webarchive.me/geocities/Tokyo/Pagoda/1641"
  },
  {
    "url": "http://www.black-sabbath.de/bsfcd.html"
  },
  {
    "url": "https://xent.com/FoRK-archive/july99"
  },
  {
    "url": "https://people.freebsd.org/~phk"
  },
  {
    "url": "http://hungry.org/"
  },
  {
    "url": "http://frogfind.de/about.php?lg=en-us"
  },
  {
    "url": "http://xahlee.info/comp/comp_index.html"
  },
  {
    "url": "https://www.cyber-rights.net/oimap.htm"
  },
  {
    "url": "https://old.cescg.org/CESCG99/DHanuska"
  },
  {
    "url": "http://mac-classic.com/"
  },
  {
    "url": "http://1997.webhistory.org/historyday"
  },
  {
    "url": "https://sed.sourceforge.io/"
  },
  {
    "url": "https://whatwg.org/validator"
  },
  {
    "url": "http://www.yoursmokiesdirectory.com/smokiesrealestatetn.html"
  },
  {
    "url": "https://howardwiseman.me/DECB/DECBmaps.html"
  },
  {
    "url": "http://ecstasy.org/experiences/trip42.html"
  },
  {
    "url": "https://justfuckingusehtml.com/"
  },
  {
    "url": "http://webarchive.me/geocities/Tokyo/Fuji/2762/obsessed.html"
  },
  {
    "url": "https://www.w3.org/TR/REC-html40"
  },
  {
    "url": "http://greatlinks.great-site.net/ecards.html"
  },
  {
    "url": "https://www.qsl.net/ac6la/moxgen.html"
  },
  {
    "url": "https://www.apa.org/practice/dsm97.html"
  },
  {
    "url": "http://richfiles.solarbotics.net/TISoft.html"
  },
  {
    "url": "https://www.besucherzaehler-html.de/"
  },
  {
    "url": "https://ctrl-c.club/~lettuce/computer-systems-social-networks.html"
  },
  {
    "url": "http://users.fred.net/kathy//bsw.html"
  },
  {
    "url": "http://web.stanford.edu/group/virus/bunya/links.html"
  },
  {
    "url": "https://lynx.invisible-island.net/lynx.html"
  },
  {
    "url": "https://tldp.org/LDP/tlk/ds/ds.html"
  },
  {
    "url": "https://home.samfundet.no/~wiesener/iopener/windows.html"
  },
  {
    "url": "https://www.formmail.com/contact"
  },
  {
    "url": "http://hopeandallen.com/Today/Broadcast.html"
  },
  {
    "url": "http://4unitmaths.com/cdromtodaycds.html"
  },
  {
    "url": "https://krzysckh.org/b/Simpler-FFI-in-Owl-Lisp.html"
  },
  {
    "url": "http://www.unicon.org/faq.html"
  },
  {
    "url": "https://kurb42.tilde.institute/blog/0001.html"
  },
  {
    "url": "https://www.htmlhelp.com/"
  },
  {
    "url": "https://webguide.neocities.org/"
  },
  {
    "url": "https://www.ditext.com/hick/8.html"
  },
  {
    "url": "http://www.tfrid.com/pictures/Megatron/Megatron.html"
  },
  {
    "url": "http://www.blencowefamilies.com/reunion/2023/BFAinvitation2023reunion.html"
  },
  {
    "url": "http://raf-112-squadron.org/index3.html"
  },
  {
    "url": "http://www.retroarchive.org/cdrom/garbo_dos/index.html"
  },
  {
    "url": "https://ed-thelen.org/Sage-Talk.html"
  },
  {
    "url": "http://iteslj.org/cw/1/ck-metalsa.html"
  },
  {
    "url": "http://www.artsci.net/html.html"
  }
]